lightning_text/__about__.py
lightning_text/__init__.py
lightning_text/_classifier.py
lightning_text/_dataset.py
lightning_text/_fasttext.py
lightning_text/_fasttext_configuration.py
lightning_text/_fasttext_defaults.py
lightning_text/_fasttext_hyperparameters.py
lightning_text/_preprocessing.py
lightning_text/_scoring.py
lightning_text/optuna.py
lightning_text-1.0.0.dist-info/METADATA
lightning_text-1.0.0.dist-info/WHEEL
lightning_text-1.0.0.dist-info/licenses/LICENSE
lightning_text-1.0.0.dist-info/RECORD
