Metadata-Version: 2.4
Name: lightning-text
Version: 1.0.0
Summary: Adapter for using FastText library with scikit-learn and optuna.
Project-URL: Documentation, https://github.com/seznam/lightning-text#readme
Project-URL: Issues, https://github.com/seznam/lightning-text/issues
Project-URL: Source, https://github.com/seznam/lightning-text
Author-email: Martin Jurča <martin.jurca@firma.seznam.cz>
License-Expression: MIT
License-File: LICENSE
Classifier: Development Status :: 5 - Production/Stable
Classifier: License :: OSI Approved :: MIT License
Classifier: Operating System :: OS Independent
Classifier: Programming Language :: Python
Classifier: Programming Language :: Python :: 3.10
Classifier: Programming Language :: Python :: 3.11
Classifier: Programming Language :: Python :: 3.12
Classifier: Programming Language :: Python :: 3.13
Classifier: Programming Language :: Python :: 3.14
Classifier: Typing :: Typed
Requires-Python: >=3.10
Requires-Dist: fasttext>=0.9.3
Requires-Dist: numpy>=2.0.0
Requires-Dist: scikit-learn>=1.6
Provides-Extra: optuna
Requires-Dist: optuna>=4.0.0; extra == 'optuna'
